<colors query="germ">

<color name="white" weight="0.528063947639">
 <shade name="weak" weight="0.38077099854" />
 <shade name="warm" weight="0.33143522132" />
 <shade name="light" weight="0.28779203378" />
</color>

<color name="black" weight="0.172065780691">
 <shade name="weak" weight="0.38077099854" />
 <shade name="warm" weight="0.33143522132" />
 <shade name="light" weight="0.28779203378" />
</color>

<color name="green" weight="0.142399266779">
 <shade name="weak" weight="0.421272803965" />
 <shade name="light" weight="0.318403863462" />
 <shade name="fresh" weight="0.260321400457" />
</color>

<color name="orange" weight="0.0900675362378">
 <shade name="weak" weight="0.38077099854" />
 <shade name="warm" weight="0.33143522132" />
 <shade name="light" weight="0.28779203378" />
</color>

<color name="blue" weight="0.0674023196088">
 <shade name="weak" weight="0.421272803965" />
 <shade name="light" weight="0.318403863462" />
 <shade name="fresh" weight="0.260321400457" />
</color>

</colors>